[{"notificationsSent":false,"_id":"5887ae4e92633d12021d1365","endDate":"2014-01-11T00:00:00.000Z","startDate":"2014-01-11T00:00:00.000Z","city":"Johannesburg","address":"27 Voortrekker Street, Edenvale, Johannesburg","registrationName":"SouthAfricaOpen2014","name":"South Africa Open 2014","province":"Gauteng"},{"notificationsSent":false,"_id":"5887ae4e92633d12021d1366","endDate":"2014-11-23T00:00:00.000Z","startDate":"2014-11-23T00:00:00.000Z","city":"Johannesburg","address":"Corner of Miriam Makeba & President Street, Johannesburg,","registrationName":"Johannesburg2014","name":"Johannesburg 2014","province":"Gauteng"},{"notificationsSent":false,"_id":"5887ae4e92633d12021d1367","endDate":"2014-11-30T00:00:00.000Z","startDate":"2014-11-30T00:00:00.000Z","city":"Cape Town","address":"370B Main Road, Observatory, Cape Town","registrationName":"CapeTown2014","name":"Cape Town 2014","province":"Western Cape"},{"notificationsSent":false,"_id":"5887ae4e92633d12021d1368","endDate":"2015-02-21T00:00:00.000Z","startDate":"2015-02-21T00:00:00.000Z","city":"Johannesburg","address":"14th Avenue Benoni","registrationName":"PopsToysSummer2015","name":"Pops Toys Summer 2015","venue":"Northmead Square","province":"Gauteng"},{"notificationsSent":false,"_id":"5887ae4e92633d12021d1369","endDate":"2015-03-28T00:00:00.000Z","startDate":"2015-03-28T00:00:00.000Z","city":"Pretoria","address":"Cnr Lynnwood Road and Roper Street, Hatfield","registrationName":"TuksOpen2015","name":"Tuks Open 2015","venue":"University of Pretoria","province":"Gauteng"},{"notificationsSent":false,"_id":"5887ae4e92633d12021d136a","endDate":"2015-04-19T00:00:00.000Z","startDate":"2015-04-19T00:00:00.000Z","city":"Cape Town","address":"370B Main Rd, Observatory, Cape Town","registrationName":"CapeTown2015","name":"Cape Town 2015","province":"Western Cape"},{"notificationsSent":false,"_id":"5887ae4e92633d12021d136b","endDate":"2015-06-27T00:00:00.000Z","startDate":"2015-06-27T00:00:00.000Z","city":"Pretoria","address":"Lynwood road Hatfield Pretoria","registrationName":"TuksWinter2015","name":"Tuks Winter 2015","venue":"University of Pretoria","province":"Gauteng"},{"notificationsSent":false,"_id":"5887ae4e92633d12021d136c","endDate":"2015-07-25T00:00:00.000Z","startDate":"2015-07-25T00:00:00.000Z","city":"Kimberley","address":"4 Fabricia Road, Kimberley, South Africa 8301","registrationName":"KimberleyOpen2015","name":"Kimberley Open 2015","venue":"City Of Hope Christian Church","province":"Northern Cape"},{"notificationsSent":false,"_id":"5887ae4e92633d12021d136d","endDate":"2015-08-08T00:00:00.000Z","startDate":"2015-08-08T00:00:00.000Z","city":"Pretoria","address":"Lynnwood Road, Hatfield, Pretoria","registrationName":"PretoriaScienceWeek2015","name":"Pretoria Science Week 2015","venue":"University of Pretoria","province":"Gauteng"},{"notificationsSent":false,"_id":"5887ae4e92633d12021d136e","endDate":"2015-08-29T00:00:00.000Z","startDate":"2015-08-29T00:00:00.000Z","city":"Benoni","address":"14th Avenue, Benoni","registrationName":"PopsWinter2015","name":"Pops Winter 2015","venue":"Northmead Square","province":"Gauteng"},{"notificationsSent":false,"_id":"5887ae4e92633d12021d136f","endDate":"2015-11-30T00:00:00.000Z","startDate":"2015-11-29T00:00:00.000Z","city":"Johannesburg","address":"CHABAD OF STRATHAVON, 2 Gayre Drive, Sandown Ext 9, 2196 Santon, South Africa","registrationName":"JohannesburgOpen2015","name":"Johannesburg Open 2015","venue":"Chabad of Strathavon","province":"Gauteng"},{"notificationsSent":false,"_id":"5887ae4e92633d12021d1370","endDate":"2015-12-07T00:00:00.000Z","startDate":"2015-12-06T00:00:00.000Z","city":"Cape Town","address":"370B Main Road, Observatory, Cape Town","registrationName":"CapetownOpen2015","name":"Cape Town Open 2015","venue":"Cape Town Science Centre","province":"Western Cape"},{"notificationsSent":false,"_id":"5887ae4e92633d12021d1371","endDate":"2016-02-13T00:00:00.000Z","startDate":"2016-02-13T00:00:00.000Z","city":"Pretoria","address":"Lynwood road Hatfield Pretoria","registrationName":"BignWeird2016","name":"Big 'n Weird Pretoria 2016","venue":"University of Pretoria","province":"Gauteng"},{"notificationsSent":false,"_id":"5887ae4e92633d12021d1372","endDate":"2016-06-19T00:00:00.000Z","startDate":"2016-06-19T00:00:00.000Z","city":"Johannesburg","address":"2 Gayre Drive, Sandown Ext 9, 2196 Santon, South Africa","registrationName":"JohannesburgOpen2016","name":"Johannesburg Open 2016","venue":"Chabad of Strathavon","province":"Gauteng"},{"notificationsSent":false,"_id":"5887ae4e92633d12021d1373","endDate":"2016-06-26T00:00:00.000Z","startDate":"2016-06-26T00:00:00.000Z","city":"Cape Town","address":"370B Main Road, Observatory, Cape Town","registrationName":"CapeTownOpen2016","name":"Cape Town Open 2016","venue":"Cape Town Science Centre","province":"Western Cape"},{"notificationsSent":false,"_id":"5887ae4e92633d12021d1374","endDate":"2016-11-27T00:00:00.000Z","startDate":"2016-11-27T00:00:00.000Z","city":"Johannesburg","address":"2 Gayre Drive, Sandown Ext 9, 2196 Santon, South Africa","registrationName":"Johannesburg2016","name":"Johannesburg 2016","venue":"Chabad of Strathavon","province":"Gauteng"},{"notificationsSent":false,"_id":"5887ae4e92633d12021d1375","endDate":"2016-12-04T00:00:00.000Z","startDate":"2016-12-04T00:00:00.000Z","city":"Cape Town","address":"370B Main Road, Observatory, Cape Town","registrationName":"CapeTown2016","name":"Cape Town 2016","venue":"Cape Town Science Centre","province":"Western Cape"},{"notificationsSent":false,"_id":"592db68c3bd2252f085ca4f8","name":"Gauteng Winter 2017","venue":"23rd Lyttelton Scout Hall","address":"209 Retief Avenue, Lyttelton Manor, Centurion","city":"Pretoria","province":"Gauteng","registrationName":"GautengWinter2017","startDate":"2017-07-08T18:13:30.665Z","endDate":"2017-07-08T18:13:30.665Z","__v":0},{"notificationsSent":false,"_id":"592db70e3bd2252f085ca4f9","name":"Eden Village Winter 2017","venue":"Seared Restaurant","address":"Eden Village, Foxhill, Salt Rock, KwaZulu Natal","city":"Salt Rock","province":"Kwa-Zulu Natal","registrationName":"EdenVillageWinter2017","startDate":"2017-07-15T18:14:42.073Z","endDate":"2017-07-15T18:14:42.073Z","__v":0},{"notificationsSent":false,"_id":"5997fb843bd2252f085ca509","name":"Speedcubes.co.za Johannesburg 2017","venue":"Chabad of Strathavon","address":"2 Gayre Dr, Strathavon, Sandton, 2031, South Africa","city":"Johannesburg","province":"Gauteng","registrationName":"Johannesburg2017","startDate":"2017-09-10T08:48:02.471Z","endDate":"2017-09-10T08:48:02.471Z","__v":0},{"notificationsSent":false,"_id":"59a1acb63bd2252f085ca50a","name":"Big 'n Weird Pretoria 2017","venue":"Sci-Enza Science Centre, University of Pretoria","address":"University of Pretoria, 50 Lynnwood Rd, Pretoria, 0011, South Africa","city":"Pretoria","province":"Gauteng","registrationName":"BignWeirdPretoria2017","startDate":"2017-09-30T17:13:19.930Z","endDate":"2017-09-30T17:13:19.930Z","__v":0},{"notificationsSent":false,"_id":"59d329be3bd2252f085ca510","name":"Speedcubes Cape Town 2017","venue":"Cape Town Science Center","address":"370B Main Rd, Observatory, 7925, South Africa","city":"Cape Town","province":"Western Cape","registrationName":"SpeedcubesCapeTown2017","startDate":"2017-11-05T06:09:16.673Z","endDate":"2017-11-05T06:09:16.673Z","__v":0},{"notificationsSent":false,"_id":"5a6e02b53bd2252f085ca516","name":"Arnold Classic Africa 2018","venue":"Sandton Convention Centre","address":"161 Maude St, Sandown, Sandton, 2031, South Africa","city":"Johannesburg","province":"Gauteng","registrationName":"ArnoldClassicAfrica2018","startDate":"2018-05-18T17:03:44.641Z","endDate":"2018-05-20T17:03:44.641Z","__v":0},{"notificationsSent":false,"_id":"5a83d8313bd2252f085ca518","name":"Gauteng Autumn 2018","venue":"23rd Lyttelton Scout Hall","address":"209 Retief Avenue, Lyttelton Manor, Centurion","city":"Pretoria","province":"Gauteng","registrationName":"GautengAutumn2018","startDate":"2018-03-24T06:32:27.755Z","endDate":"2018-03-24T06:32:27.755Z","__v":0},{"notificationsSent":false,"_id":"5aa15d793bd2252f085ca51a","name":"Speedcubes Cape Town 2018","venue":"Cape Town Science Center","address":"370B Main Rd, Observatory, 7925, South Africa","city":"Cape Town","province":"Western Cape","registrationName":"SpeedcubesCapeTown2018","startDate":"2018-04-09T15:52:59.480Z","endDate":"2018-04-09T15:52:59.480Z","__v":0},{"notificationsSent":false,"_id":"5b6806b03bd2252f085ca523","name":"Soweto Spring Open 2018","venue":"Maponya Mall","address":"Chris Hani Road, Soweto","city":"Johannesburg","province":"Gauteng","registrationName":"SowetoSpringOpen2018","startDate":"2018-09-08T08:27:12.823Z","endDate":"2018-09-08T08:27:12.823Z","__v":0},{"notificationsSent":false,"_id":"5be42fa33bd2252f085ca528","name":"Gauteng Summer 2019","venue":"1st Greenside Scout Hall","address":"47 John McKenzie Drive Victory Park, Emmarentia","city":"Johannesburg","province":"Gauteng","registrationName":"GautengSummer2019","startDate":"2019-01-05T12:42:56.083Z","endDate":"2019-01-05T12:42:56.083Z","__v":0},{"notificationsSent":false,"_id":"5c2487444ce2710a26fa45f9","name":"Speedcubes Cape Town 2019","venue":"Cape Town Science Center","address":"370B Main Rd, Observatory, 7925, South Africa","city":"Cape Town","province":"Gauteng","registrationName":"SpeedcubesCapeTown2019","startDate":"2019-01-20T08:02:00.479Z","endDate":"2019-01-20T08:02:00.480Z","__v":0},{"notificationsSent":false,"_id":"5c9864e71e18cf5edfb4291a","name":"Arnold Classic Africa 2019","venue":"Sandton Convention Centre","address":"161 Maude St, Sandown, Sandton, 2031, South Africa","city":"Johannesburg","province":"Gauteng","registrationName":"ArnoldClassicAfrica2019","startDate":"2019-05-17T05:18:45.184Z","endDate":"2019-05-19T05:18:45.184Z","__v":0},{"notificationsSent":false,"_id":"5c98655e1e18cf5edfb4291b","name":"FMC 2019","venue":"Opti-Num Solutions","address":"Ground Floor, Northview, 57 Sixth Road, Hyde Park, Johannesburg 2196","city":"Johannesburg","province":"Gauteng","registrationName":"FMC2019","startDate":"2019-06-15T05:19:50.649Z","endDate":"2019-06-15T05:19:50.649Z","__v":0},{"notificationsSent":false,"_id":"5ca260f41e18cf5edfb4291c","name":"Campus Classic Cape Town 2019","venue":"Smuts Hall Dinning Room, University of Cape Town","address":"Residence Street, University of Cape Town, Rondebosch, Cape Town, 7700","city":"Cape Town","province":"Western Cape","registrationName":"CampusClassicCapeTown2019","startDate":"2019-04-28T19:04:21.688Z","endDate":"2019-04-28T19:04:21.688Z","__v":0},{"notificationsSent":false,"_id":"5ca261411e18cf5edfb4291d","name":"KwaZulu-Natal 2019","venue":"The Creative Classroom","address":"2 Old Main Road, Umhlali, Durban, 4390","city":"Salt Rock","province":"KwaZulu Natal","registrationName":"KwaZuluNatal2019","startDate":"2019-04-27T19:05:52.585Z","endDate":"2019-04-27T19:05:52.585Z","__v":0},{"notificationsSent":false,"_id":"5d87bb631e18cf5edfb4293a","name":"Cape Town Spring 2019","venue":"Kirstenhof Primary School","address":"18 Lente St, Kirstenhof, Cape Town","city":"Cape Town","province":"Western Cape","registrationName":"CapeTownSpring2019","startDate":"2019-10-20T18:18:57.780Z","endDate":"2019-10-20T18:18:57.780Z","__v":0},{"notificationsSent":false,"_id":"5e4bbd044f37e12778a918b1","name":"Cape Town Summer 2020","venue":"Kirstenhof Primary School","address":"18 Lente St, Kirstenhof, Cape Town, South Africa","city":"Cape Town","province":"Western Cape","registrationName":"CapeTownSummer2020","startDate":"2020-03-14T10:30:39.631Z","endDate":"2020-03-15T10:30:39.631Z","__v":0},{"notificationsSent":false,"_id":"6205300b7bd8ff3c5d4604f8","name":"Cape Town Summer 2022","venue":"Sea Point High School","address":"Main Road, Sea Point, Cape Town, 8005","city":"Cape Town","province":"Western Cape","registrationName":"CapeTownSummer2022","startDate":"2022-03-06T15:31:20.954Z","endDate":"2022-03-06T15:31:20.954Z","__v":0},{"notificationsSent":false,"_id":"6241a81c4aa6f913f65c663e","name":"Speedcubes Cape Town 2022","venue":"Sea Point High School","address":"Main Rd, Sea Point, Cape Town, 8005","city":"Cape Town","province":"Western Cape","registrationName":"SpeedcubesCapeTown2022","startDate":"2022-05-29T12:19:59.536Z","endDate":"2022-05-29T12:19:59.536Z","__v":0},{"notificationsSent":false,"_id":"6255a8144aa6f913f65c6798","name":"Gauteng Autumn 2022","venue":"Fayview Function Venue","address":"152 President Boshoff Rd, Rynfield AH, Benoni, 1501","city":"Ekurhuleni","province":"Gauteng","registrationName":"GautengAutumn2022","startDate":"2022-05-15T16:25:11.664Z","endDate":"2022-05-15T16:25:11.664Z","__v":0},{"notificationsSent":false,"_id":"626b806b4aa6f913f65c69ad","name":"Arnold Classic Africa 2022","venue":"Ruimsig Stadium","address":"Ruimsig Stadium, Roodepoort, South Africa","city":"Johannesburg","province":"Gauteng","registrationName":"ArnoldClassicAfrica2022","startDate":"2022-06-03T06:05:55.511Z","endDate":"2022-06-05T06:05:55.511Z","__v":0},{"notificationsSent":false,"_id":"62b74d1b4aa6f913f65c70e1","name":"Rubik's WCA African Championship 2022","venue":"GrandWest Casino and Entertainment World","address":"1 Jakes Gerwel Drive, Goodwood, Cape Town, 7460","city":"Cape Town","province":"Western Cape","registrationName":"WCAAfricanChampionship2022","startDate":"2022-10-07T17:58:59.190Z","endDate":"2022-10-09T17:58:59.190Z","__v":0},{"notificationsSent":false,"_id":"62c5548d4aa6f913f65c71d8","name":"CubeCo Durban Winter Warmup 2022","venue":"Winston Park Primary School","address":"Jan Smuts Ave, Winston Park, Durban, 3610","city":"Durban","province":"KwaZulu Natal","registrationName":"CubeCoDurbanWinterWarmup2022","startDate":"2022-07-30T09:21:54.141Z","endDate":"2022-07-31T09:21:54.141Z","__v":0},{"notificationsSent":false,"_id":"62ceeb604aa6f913f65c7284","name":"Limpopo 2022","venue":"Hoërskool Pietersburg","address":"125 Dorp St, Polokwane Ext 4 (W), Polokwane, 0700","city":"Polokwane","province":"Limpopo","registrationName":"Limpopo2022","startDate":"2022-08-06T15:56:32.508Z","endDate":"2022-08-06T15:56:32.508Z","__v":0},{"notificationsSent":false,"_id":"62ec02a64aa6f913f65c746b","name":"Green School Paarl Open 2022","venue":"Green School","address":"R45, Paarl, 7646","city":"Paarl","province":"Western Cape","registrationName":"GreenSchoolPaarlOpen2022","startDate":"2022-08-28T17:30:47.597Z","endDate":"2022-08-28T17:30:47.597Z","__v":0},{"notificationsSent":false,"_id":"630df31a4aa6f913f65c7636","name":"Inni-Horie-Fees Speedcubing 2022","venue":"Laerskool Horison","address":"48 Mouton Rd, Horison, Roodepoort, 1724","city":"Johannesburg","province":"Gauteng","registrationName":"InniHorieFeesSpeedcubing2022","startDate":"2022-09-24T11:22:26.858Z","endDate":"2022-09-24T11:22:26.858Z","__v":0},{"notificationsSent":false,"_id":"633839cf4aa6f913f65c7988","name":"Just Cube Joburg 2022","venue":"Greenside Primary School","address":"Vardon Rd, Greenside, Johannesburg, 2193","city":"Johannesburg","province":"Gauteng","registrationName":"JustCubeJoburg2022","startDate":"2022-11-12T12:58:17.291Z","endDate":"2022-11-13T12:58:17.291Z","__v":0},{"notificationsSent":false,"_id":"635799d34aa6f913f65c7ba6","name":"Mimosa Mall Master Cubers 2022","venue":"Mimosa Mall","address":"131 Kellner St., Brandwag, Bloemfontein, 9301","city":"Bloemfontein","province":"Free State","registrationName":"MimosaMallMasterCubers2022","startDate":"2022-11-19T08:08:56.421Z","endDate":"2022-11-19T08:08:56.421Z","__v":0},{"notificationsSent":false,"_id":"6368a0834aa6f913f65c7c7e","name":"CubeCo Durban Summer 2022","venue":"Winston Park Primary School","address":"Jan Smuts Ave, Winston Park, Durban, 3610","city":"Durban","province":"KwaZulu Natal","registrationName":"CubeCoDurbanSummer2022","startDate":"2022-12-03T06:06:06.809Z","endDate":"2022-12-04T06:06:06.809Z","__v":0},{"notificationsSent":true,"_id":"123839cf4aa6f913f65c7988","name":"Far Future Comp 2345","venue":"Place","address":"1 Street, City","city":"City","province":"KwaZulu Natal","registrationName":"FarFutureComp2345","startDate":"2345-12-03T06:06:06.809Z","endDate":"2345-12-04T06:06:06.809Z","__v":0},{"notificationsSent":false,"_id":"456839cf4aa6f913f65c7988","name":"Some Future Comp 2121","venue":"Place","address":"1 Street, City","city":"City","province":"KwaZulu Natal","registrationName":"SomeFutureComp2121","startDate":"2121-12-03T06:06:06.809Z","endDate":"2121-12-03T06:06:06.809Z","__v":0}]